{
  "id": 71875,
  "name": "BreadTalk - AEON Mall Tân Phú",
  "address": "Tầng Trệt AEON Mall Tân Phú, 30 Bờ Bao Tân Thắng, P. Sơn Kỳ, Quận Tân Phú, TP. HCM",
  "rating": 7.276,
  "total_reviews": 50,
  "total_pictures": 299,
  "phone": "(028) 38 472 085",
  "photo_url": "https://images.foody.vn/res/g8/71875/prof/s640x400/vn-11134513-7r98o-lsts17dines9f3",
  "url": "https://www.foody.vn/ho-chi-minh/bread-talk-aeon-mall",
  "location": {
    "lat": 10.801473,
    "lon": 106.617953
  },
  "reviews": [
    {
      "user": "T4_ eattheworld",
      "rating": 7.4,
      "comment": "Bánh đa dạng, ngon 👍🏻\nKhông gian nhỏ nhỏ xinh xinh nè ☺️&nbsp; &nbsp; &nbsp; &nbsp; &nbsp; &nbsp; &nbsp; &nbsp; &nbsp; &nbsp; &nbsp; ",
      "date": null,
      "user_avatar": "https://images.foody.vn/usr/g60/590575/avt/c100x100/chillyt4-avatar-212-638097331971690763.jpg"
    },
    {
      "user": "Mio Phan",
      "rating": 8.6,
      "comment": "Hồi đợt chơi game của bread được voucher 50k nên mình ghé mua. Đi chi nhánh này cho gần nhà ))))\nQuán nằm trong khu vực tầng trệt, không gian cũng thoáng có bàn ngồi lại tầm 3,4 bàn\nKhu bánh thì mình ...",
      "date": null,
      "user_avatar": "https://images.foody.vn/usr/g157/1568580/avt/c100x100/trucmai1107-avatar-955-637504094024492453.jpg"
    }
  ],
  "services": [
    {
      "name": "ShopeeFood",
      "url": "https://www.deliverynow.vn/ho-chi-minh/bread-talk-aeon-mall",
      "type": 0
    }
  ],
  "is_delivery": true,
  "is_booking": false,
  "is_opening": true,
  "price_range": {
    "min": null,
    "max": null
  },
  "crawled_at": "2025-04-19T19:57:38.926447"
}